eochat_qt/__init__.py
eochat_qt/config.py
eochat_qt/eo_defs.py
eochat_qt/helpers.py
eochat_qt/main.py
eochat_qt/mainwindow.py
eochat_qt-0.3.0.dist-info/LICENSE
eochat_qt-0.3.0.dist-info/METADATA
eochat_qt-0.3.0.dist-info/WHEEL
eochat_qt-0.3.0.dist-info/entry_points.txt
eochat_qt-0.3.0.dist-info/top_level.txt
eochat_qt-0.3.0.dist-info/RECORD
